openrubricrl/__init__.py
openrubricrl/cli.py
openrubricrl/api/__init__.py
openrubricrl/api/models.py
openrubricrl/api/server.py
openrubricrl/core/__init__.py
openrubricrl/core/prompt_builder.py
openrubricrl/core/reward_processor.py
openrubricrl/core/rubric.py
openrubricrl/core/scorer.py
openrubricrl/integrations/__init__.py
openrubricrl/integrations/base.py
openrubricrl/integrations/cleanrl.py
openrubricrl/integrations/rllib.py
openrubricrl/integrations/trl.py
openrubricrl/logging/__init__.py
openrubricrl/logging/logger.py
openrubricrl/logging/storage.py
openrubricrl-0.1.0.dist-info/METADATA
openrubricrl-0.1.0.dist-info/WHEEL
openrubricrl-0.1.0.dist-info/entry_points.txt
openrubricrl-0.1.0.dist-info/top_level.txt
openrubricrl-0.1.0.dist-info/RECORD
