Metadata-Version: 2.4
Name: openrubricrl
Version: 0.1.0
Summary: Open-source pipeline that converts human-written rubrics into LLM-based reward functions for RL and RLHF training
Author-email: OpenRubricRL Team <anikal2001@gmail.com>
License: MIT
Project-URL: Homepage, https://github.com/openrubricrl/openrubricrl
Project-URL: Repository, https://github.com/openrubricrl/openrubricrl
Project-URL: Documentation, https://openrubricrl.readthedocs.io
Project-URL: Bug Tracker, https://github.com/openrubricrl/openrubricrl/issues
Keywords: rlhf,reinforcement-learning,llm,reward-function,rubric
Classifier: Development Status :: 3 - Alpha
Classifier: Intended Audience :: Developers
Classifier: Intended Audience :: Science/Research
Classifier: License :: OSI Approved :: MIT License
Classifier: Programming Language :: Python :: 3
Classifier: Programming Language :: Python :: 3.8
Classifier: Programming Language :: Python :: 3.9
Classifier: Programming Language :: Python :: 3.10
Classifier: Programming Language :: Python :: 3.11
Classifier: Topic :: Scientific/Engineering :: Artificial Intelligence
Classifier: Topic :: Software Development :: Libraries :: Python Modules
Requires-Python: >=3.8
Requires-Dist: fastapi>=0.104.0
Requires-Dist: uvicorn[standard]>=0.24.0
Requires-Dist: pydantic>=2.0.0
Requires-Dist: pyyaml>=6.0
Requires-Dist: jsonschema>=4.17.0
Requires-Dist: openai>=1.0.0
Requires-Dist: anthropic>=0.7.0
Requires-Dist: click>=8.0.0
Requires-Dist: aiohttp>=3.8.0
Requires-Dist: python-multipart>=0.0.6
Provides-Extra: dev
Requires-Dist: pytest>=7.0.0; extra == "dev"
Requires-Dist: pytest-asyncio>=0.21.0; extra == "dev"
Requires-Dist: black>=23.0.0; extra == "dev"
Requires-Dist: isort>=5.0.0; extra == "dev"
Requires-Dist: flake8>=6.0.0; extra == "dev"
Requires-Dist: mypy>=1.0.0; extra == "dev"
Requires-Dist: pre-commit>=3.0.0; extra == "dev"
Provides-Extra: local
Requires-Dist: vllm>=0.2.0; extra == "local"
Requires-Dist: transformers>=4.30.0; extra == "local"
Requires-Dist: torch>=2.0.0; extra == "local"
Provides-Extra: metrics
Requires-Dist: nltk>=3.8.0; extra == "metrics"
Requires-Dist: rouge-score>=0.1.2; extra == "metrics"
Requires-Dist: sacrebleu>=2.3.0; extra == "metrics"
Requires-Dist: scikit-learn>=1.3.0; extra == "metrics"
Provides-Extra: all
Requires-Dist: openrubricrl[dev,local,metrics]; extra == "all"
